nsj_flask_auth/__init__.py
nsj_flask_auth/auth.py
nsj_flask_auth/caching.py
nsj_flask_auth/exceptions.py
nsj_flask_auth/settings.py
nsj_flask_auth-0.10.0.dist-info/METADATA
nsj_flask_auth-0.10.0.dist-info/WHEEL
nsj_flask_auth-0.10.0.dist-info/RECORD
